{
  "updated_at": "2026-05-14 18:36:24",
  "updated_at_iso": "2026-05-14T18:36:24.766925+09:00",
  "total_stocks": 20,
  "errors": 0,
  "stocks": [
    {
      "code": "4183.T",
      "name": "三井化学",
      "sector": "素材",
      "theme": "半導体ペリクル等の機能性材料。PBR1倍割れ修正期待",
      "risk": "中",
      "error": false,
      "date": "2026-05-14",
      "close": 2167.5,
      "open": 2080.5,
      "change": 168.5,
      "change_pct": 8.43,
      "ma5": 1989.9,
      "ma25": 1962.2,
      "ma75": 2062.1,
      "rsi": 67.1,
      "macd": 11.6,
      "macd_signal": -8.7,
      "bb_upper": 2085.3,
      "bb_lower": 1833.2,
      "vol_ratio": 2.13,
      "signals": {
        "ma": {
          "score": 2,
          "label": "GC発生",
          "icon": "✨",
          "type": "buy"
        },
        "rsi": {
          "score": 1,
          "label": "RSI 67.1",
          "icon": "💪",
          "type": "buy"
        },
        "macd": {
          "score": 1,
          "label": "MACD強気",
          "icon": "🔺",
          "type": "buy"
        },
        "bb": {
          "score": 2,
          "label": "バンドウォーク",
          "icon": "🚀",
          "type": "buy"
        },
        "vol": {
          "score": 2,
          "label": "出来高2.1倍↑",
          "icon": "🔊",
          "type": "buy"
        }
      },
      "total_score": 8,
      "overall": {
        "label": "強い買い",
        "color": "#00e896",
        "icon": "🟢🟢"
      },
      "checks": [
        {
          "label": "MA上向き＋株価がMA上",
          "ok": true
        },
        {
          "label": "日足押し目 RSI 40-60圏",
          "ok": false
        },
        {
          "label": "直近陽線 or 5MA反発確認",
          "ok": true
        },
        {
          "label": "出来高20日平均以上",
          "ok": true
        }
      ]
    },
    {
      "code": "8306.T",
      "name": "三菱UFJ FG",
      "sector": "金融",
      "theme": "メガバンク最大手。金利上昇で利ざや拡大",
      "risk": "低",
      "error": false,
      "date": "2026-05-14",
      "close": 2877.0,
      "open": 2920.5,
      "change": -49.5,
      "change_pct": -1.69,
      "ma5": 2870.5,
      "ma25": 2844.3,
      "ma75": 2788.2,
      "rsi": 54.6,
      "macd": 27.3,
      "macd_signal": 23.4,
      "bb_upper": 2951.1,
      "bb_lower": 2742.5,
      "vol_ratio": 0.96,
      "signals": {
        "ma": {
          "score": 1,
          "label": "MA上昇中",
          "icon": "↗",
          "type": "buy"
        },
        "rsi": {
          "score": 2,
          "label": "RSI 54.6 押し目",
          "icon": "🎯",
          "type": "buy"
        },
        "macd": {
          "score": 1,
          "label": "MACD強気",
          "icon": "🔺",
          "type": "buy"
        },
        "bb": {
          "score": 1,
          "label": "上半分推移",
          "icon": "📊",
          "type": "buy"
        },
        "vol": {
          "score": 0,
          "label": "1.0倍",
          "icon": "📊",
          "type": "neutral"
        }
      },
      "total_score": 5,
      "overall": {
        "label": "強い買い",
        "color": "#00e896",
        "icon": "🟢🟢"
      },
      "checks": [
        {
          "label": "MA上向き＋株価がMA上",
          "ok": true
        },
        {
          "label": "日足押し目 RSI 40-60圏",
          "ok": true
        },
        {
          "label": "直近陽線 or 5MA反発確認",
          "ok": false
        },
        {
          "label": "出来高20日平均以上",
          "ok": false
        }
      ]
    },
    {
      "code": "8766.T",
      "name": "東京海上HD",
      "sector": "金融",
      "theme": "損保最大手。保険料値上げ＋金利上昇のダブルメリット",
      "risk": "低",
      "error": false,
      "date": "2026-05-14",
      "close": 7362.0,
      "open": 7369.0,
      "change": -7.0,
      "change_pct": -0.09,
      "ma5": 7210.2,
      "ma25": 7148.6,
      "ma75": 6528.6,
      "rsi": 59.8,
      "macd": 104.2,
      "macd_signal": 108.6,
      "bb_upper": 7394.5,
      "bb_lower": 6846.9,
      "vol_ratio": 0.68,
      "signals": {
        "ma": {
          "score": 2,
          "label": "パーフェクトオーダー",
          "icon": "📈",
          "type": "buy"
        },
        "rsi": {
          "score": 2,
          "label": "RSI 59.8 押し目",
          "icon": "🎯",
          "type": "buy"
        },
        "macd": {
          "score": -1,
          "label": "MACD弱気",
          "icon": "▽",
          "type": "sell"
        },
        "bb": {
          "score": 2,
          "label": "バンドウォーク",
          "icon": "🚀",
          "type": "buy"
        },
        "vol": {
          "score": 0,
          "label": "0.7倍",
          "icon": "📊",
          "type": "neutral"
        }
      },
      "total_score": 5,
      "overall": {
        "label": "強い買い",
        "color": "#00e896",
        "icon": "🟢🟢"
      },
      "checks": [
        {
          "label": "MA上向き＋株価がMA上",
          "ok": true
        },
        {
          "label": "日足押し目 RSI 40-60圏",
          "ok": true
        },
        {
          "label": "直近陽線 or 5MA反発確認",
          "ok": false
        },
        {
          "label": "出来高20日平均以上",
          "ok": false
        }
      ]
    },
    {
      "code": "9984.T",
      "name": "ソフトバンクG",
      "sector": "テクノロジー",
      "theme": "AI投資の中核。ARM・ビジョンファンド",
      "risk": "高",
      "error": false,
      "date": "2026-05-14",
      "close": 5770.0,
      "open": 6100.0,
      "change": -242.0,
      "change_pct": -4.03,
      "ma5": 5928.6,
      "ma25": 5017.4,
      "ma75": 4333.8,
      "rsi": 59.4,
      "macd": 489.2,
      "macd_signal": 481.5,
      "bb_upper": 6753.5,
      "bb_lower": 3931.1,
      "vol_ratio": 0.81,
      "signals": {
        "ma": {
          "score": 1,
          "label": "MA上昇中",
          "icon": "↗",
          "type": "buy"
        },
        "rsi": {
          "score": 2,
          "label": "RSI 59.4 押し目",
          "icon": "🎯",
          "type": "buy"
        },
        "macd": {
          "score": 1,
          "label": "MACD強気",
          "icon": "🔺",
          "type": "buy"
        },
        "bb": {
          "score": 1,
          "label": "上半分推移",
          "icon": "📊",
          "type": "buy"
        },
        "vol": {
          "score": 0,
          "label": "0.8倍",
          "icon": "📊",
          "type": "neutral"
        }
      },
      "total_score": 5,
      "overall": {
        "label": "強い買い",
        "color": "#00e896",
        "icon": "🟢🟢"
      },
      "checks": [
        {
          "label": "MA上向き＋株価がMA上",
          "ok": true
        },
        {
          "label": "日足押し目 RSI 40-60圏",
          "ok": true
        },
        {
          "label": "直近陽線 or 5MA反発確認",
          "ok": false
        },
        {
          "label": "出来高20日平均以上",
          "ok": false
        }
      ]
    },
    {
      "code": "8035.T",
      "name": "東京エレクトロン",
      "sector": "AI・半導体",
      "theme": "半導体製造装置で国内最大手。AI投資拡大が追い風",
      "risk": "中",
      "error": false,
      "date": "2026-05-14",
      "close": 51200.0,
      "open": 51590.0,
      "change": -140.0,
      "change_pct": -0.27,
      "ma5": 51846.0,
      "ma25": 45873.6,
      "ma75": 42444.0,
      "rsi": 66.6,
      "macd": 2711.5,
      "macd_signal": 2269.6,
      "bb_upper": 53706.6,
      "bb_lower": 40432.4,
      "vol_ratio": 0.63,
      "signals": {
        "ma": {
          "score": 1,
          "label": "MA上昇中",
          "icon": "↗",
          "type": "buy"
        },
        "rsi": {
          "score": 1,
          "label": "RSI 66.6",
          "icon": "💪",
          "type": "buy"
        },
        "macd": {
          "score": 1,
          "label": "MACD強気",
          "icon": "🔺",
          "type": "buy"
        },
        "bb": {
          "score": 1,
          "label": "上半分推移",
          "icon": "📊",
          "type": "buy"
        },
        "vol": {
          "score": 0,
          "label": "0.6倍",
          "icon": "📊",
          "type": "neutral"
        }
      },
      "total_score": 4,
      "overall": {
        "label": "買い検討",
        "color": "#00c97a",
        "icon": "🟢"
      },
      "checks": [
        {
          "label": "MA上向き＋株価がMA上",
          "ok": true
        },
        {
          "label": "日足押し目 RSI 40-60圏",
          "ok": false
        },
        {
          "label": "直近陽線 or 5MA反発確認",
          "ok": false
        },
        {
          "label": "出来高20日平均以上",
          "ok": false
        }
      ]
    },
    {
      "code": "6861.T",
      "name": "キーエンス",
      "sector": "テクノロジー",
      "theme": "FA(工場自動化)センサー最大手。高収益体質",
      "risk": "低",
      "error": false,
      "date": "2026-05-14",
      "close": 77310.0,
      "open": 79200.0,
      "change": -2130.0,
      "change_pct": -2.68,
      "ma5": 80496.0,
      "ma25": 68414.0,
      "ma75": 61968.7,
      "rsi": 63.9,
      "macd": 5203.5,
      "macd_signal": 4386.9,
      "bb_upper": 85869.4,
      "bb_lower": 55048.6,
      "vol_ratio": 0.78,
      "signals": {
        "ma": {
          "score": 1,
          "label": "MA上昇中",
          "icon": "↗",
          "type": "buy"
        },
        "rsi": {
          "score": 1,
          "label": "RSI 63.9",
          "icon": "💪",
          "type": "buy"
        },
        "macd": {
          "score": 1,
          "label": "MACD強気",
          "icon": "🔺",
          "type": "buy"
        },
        "bb": {
          "score": 1,
          "label": "上半分推移",
          "icon": "📊",
          "type": "buy"
        },
        "vol": {
          "score": 0,
          "label": "0.8倍",
          "icon": "📊",
          "type": "neutral"
        }
      },
      "total_score": 4,
      "overall": {
        "label": "買い検討",
        "color": "#00c97a",
        "icon": "🟢"
      },
      "checks": [
        {
          "label": "MA上向き＋株価がMA上",
          "ok": true
        },
        {
          "label": "日足押し目 RSI 40-60圏",
          "ok": false
        },
        {
          "label": "直近陽線 or 5MA反発確認",
          "ok": false
        },
        {
          "label": "出来高20日平均以上",
          "ok": false
        }
      ]
    },
    {
      "code": "6506.T",
      "name": "安川電機",
      "sector": "AI・半導体",
      "theme": "産業用ロボット大手。フィジカルAI・エヌビディア連携",
      "risk": "中",
      "error": false,
      "date": "2026-05-14",
      "close": 7006.0,
      "open": 7261.0,
      "change": 26.0,
      "change_pct": 0.37,
      "ma5": 6779.4,
      "ma25": 5493.6,
      "ma75": 5061.7,
      "rsi": 81.7,
      "macd": 536.8,
      "macd_signal": 372.7,
      "bb_upper": 7021.1,
      "bb_lower": 4425.7,
      "vol_ratio": 1.28,
      "signals": {
        "ma": {
          "score": 2,
          "label": "パーフェクトオーダー",
          "icon": "📈",
          "type": "buy"
        },
        "rsi": {
          "score": -2,
          "label": "RSI 81.7 警戒",
          "icon": "🚨",
          "type": "sell"
        },
        "macd": {
          "score": 1,
          "label": "MACD強気",
          "icon": "🔺",
          "type": "buy"
        },
        "bb": {
          "score": 2,
          "label": "バンドウォーク",
          "icon": "🚀",
          "type": "buy"
        },
        "vol": {
          "score": 0,
          "label": "1.3倍",
          "icon": "📊",
          "type": "neutral"
        }
      },
      "total_score": 3,
      "overall": {
        "label": "買い検討",
        "color": "#00c97a",
        "icon": "🟢"
      },
      "checks": [
        {
          "label": "MA上向き＋株価がMA上",
          "ok": true
        },
        {
          "label": "日足押し目 RSI 40-60圏",
          "ok": false
        },
        {
          "label": "直近陽線 or 5MA反発確認",
          "ok": false
        },
        {
          "label": "出来高20日平均以上",
          "ok": true
        }
      ]
    },
    {
      "code": "8316.T",
      "name": "三井住友FG",
      "sector": "金融",
      "theme": "メガバンク。累進配当方針で株主還元強化",
      "risk": "低",
      "error": false,
      "date": "2026-05-14",
      "close": 5675.0,
      "open": 5735.0,
      "change": -177.0,
      "change_pct": -3.02,
      "ma5": 5704.6,
      "ma25": 5562.5,
      "ma75": 5471.3,
      "rsi": 54.9,
      "macd": 85.0,
      "macd_signal": 64.9,
      "bb_upper": 5840.5,
      "bb_lower": 5315.1,
      "vol_ratio": 1.58,
      "signals": {
        "ma": {
          "score": 1,
          "label": "MA上昇中",
          "icon": "↗",
          "type": "buy"
        },
        "rsi": {
          "score": 2,
          "label": "RSI 54.9 押し目",
          "icon": "🎯",
          "type": "buy"
        },
        "macd": {
          "score": 1,
          "label": "MACD強気",
          "icon": "🔺",
          "type": "buy"
        },
        "bb": {
          "score": 1,
          "label": "上半分推移",
          "icon": "📊",
          "type": "buy"
        },
        "vol": {
          "score": -2,
          "label": "出来高1.6倍↓",
          "icon": "🔕",
          "type": "sell"
        }
      },
      "total_score": 3,
      "overall": {
        "label": "買い検討",
        "color": "#00c97a",
        "icon": "🟢"
      },
      "checks": [
        {
          "label": "MA上向き＋株価がMA上",
          "ok": true
        },
        {
          "label": "日足押し目 RSI 40-60圏",
          "ok": true
        },
        {
          "label": "直近陽線 or 5MA反発確認",
          "ok": false
        },
        {
          "label": "出来高20日平均以上",
          "ok": true
        }
      ]
    },
    {
      "code": "6857.T",
      "name": "アドバンテスト",
      "sector": "AI・半導体",
      "theme": "半導体検査装置世界首位。AI半導体需要の恩恵直撃",
      "risk": "中",
      "error": false,
      "date": "2026-05-14",
      "close": 28615.0,
      "open": 28510.0,
      "change": 325.0,
      "change_pct": 1.15,
      "ma5": 28855.0,
      "ma25": 27438.2,
      "ma75": 25588.3,
      "rsi": 55.3,
      "macd": 1051.4,
      "macd_signal": 1213.3,
      "bb_upper": 31024.5,
      "bb_lower": 25657.0,
      "vol_ratio": 0.9,
      "signals": {
        "ma": {
          "score": 1,
          "label": "MA上昇中",
          "icon": "↗",
          "type": "buy"
        },
        "rsi": {
          "score": 2,
          "label": "RSI 55.3 押し目",
          "icon": "🎯",
          "type": "buy"
        },
        "macd": {
          "score": -1,
          "label": "MACD弱気",
          "icon": "▽",
          "type": "sell"
        },
        "bb": {
          "score": 0,
          "label": "バンド中央",
          "icon": "⊙",
          "type": "neutral"
        },
        "vol": {
          "score": 0,
          "label": "0.9倍",
          "icon": "📊",
          "type": "neutral"
        }
      },
      "total_score": 2,
      "overall": {
        "label": "やや強気",
        "color": "#44aadd",
        "icon": "🔵"
      },
      "checks": [
        {
          "label": "MA上向き＋株価がMA上",
          "ok": true
        },
        {
          "label": "日足押し目 RSI 40-60圏",
          "ok": true
        },
        {
          "label": "直近陽線 or 5MA反発確認",
          "ok": false
        },
        {
          "label": "出来高20日平均以上",
          "ok": false
        }
      ]
    },
    {
      "code": "6954.T",
      "name": "ファナック",
      "sector": "内需・FA",
      "theme": "CNC・ロボット世界首位。フィジカルAI本命",
      "risk": "中",
      "error": false,
      "date": "2026-05-14",
      "close": 8036.0,
      "open": 8540.0,
      "change": 356.0,
      "change_pct": 4.64,
      "ma5": 7709.0,
      "ma25": 6633.8,
      "ma75": 6350.3,
      "rsi": 73.8,
      "macd": 453.7,
      "macd_signal": 327.7,
      "bb_upper": 8024.8,
      "bb_lower": 5653.4,
      "vol_ratio": 2.08,
      "signals": {
        "ma": {
          "score": 2,
          "label": "パーフェクトオーダー",
          "icon": "📈",
          "type": "buy"
        },
        "rsi": {
          "score": -1,
          "label": "RSI 73.8 過熱",
          "icon": "🔥",
          "type": "warn"
        },
        "macd": {
          "score": 1,
          "label": "MACD強気",
          "icon": "🔺",
          "type": "buy"
        },
        "bb": {
          "score": 2,
          "label": "バンドウォーク",
          "icon": "🚀",
          "type": "buy"
        },
        "vol": {
          "score": -2,
          "label": "出来高2.1倍↓",
          "icon": "🔕",
          "type": "sell"
        }
      },
      "total_score": 2,
      "overall": {
        "label": "やや強気",
        "color": "#44aadd",
        "icon": "🔵"
      },
      "checks": [
        {
          "label": "MA上向き＋株価がMA上",
          "ok": true
        },
        {
          "label": "日足押し目 RSI 40-60圏",
          "ok": false
        },
        {
          "label": "直近陽線 or 5MA反発確認",
          "ok": false
        },
        {
          "label": "出来高20日平均以上",
          "ok": true
        }
      ]
    },
    {
      "code": "7012.T",
      "name": "川崎重工業",
      "sector": "防衛・造船",
      "theme": "防衛装備・造船・航空エンジン。水素関連も",
      "risk": "中",
      "error": false,
      "date": "2026-05-14",
      "close": 3162.0,
      "open": 3417.0,
      "change": -255.0,
      "change_pct": -7.46,
      "ma5": 3281.2,
      "ma25": 3228.6,
      "ma75": 3162.9,
      "rsi": 47.8,
      "macd": 24.2,
      "macd_signal": 15.5,
      "bb_upper": 3439.7,
      "bb_lower": 3010.7,
      "vol_ratio": 1.0,
      "signals": {
        "ma": {
          "score": -1,
          "label": "MA25割れ",
          "icon": "↘",
          "type": "sell"
        },
        "rsi": {
          "score": 2,
          "label": "RSI 47.8 押し目",
          "icon": "🎯",
          "type": "buy"
        },
        "macd": {
          "score": 1,
          "label": "MACD強気",
          "icon": "🔺",
          "type": "buy"
        },
        "bb": {
          "score": -1,
          "label": "下半分",
          "icon": "📉",
          "type": "sell"
        },
        "vol": {
          "score": 0,
          "label": "1.0倍",
          "icon": "📊",
          "type": "neutral"
        }
      },
      "total_score": 1,
      "overall": {
        "label": "やや強気",
        "color": "#44aadd",
        "icon": "🔵"
      },
      "checks": [
        {
          "label": "MA上向き＋株価がMA上",
          "ok": false
        },
        {
          "label": "日足押し目 RSI 40-60圏",
          "ok": true
        },
        {
          "label": "直近陽線 or 5MA反発確認",
          "ok": false
        },
        {
          "label": "出来高20日平均以上",
          "ok": false
        }
      ]
    },
    {
      "code": "1928.T",
      "name": "積水ハウス",
      "sector": "建設",
      "theme": "住宅大手。賃上げ・インフレ環境で内需回復期待",
      "risk": "低",
      "error": false,
      "date": "2026-05-14",
      "close": 3423.0,
      "open": 3480.0,
      "change": -77.0,
      "change_pct": -2.2,
      "ma5": 3443.8,
      "ma25": 3488.2,
      "ma75": 3558.9,
      "rsi": 43.8,
      "macd": -28.8,
      "macd_signal": -34.2,
      "bb_upper": 3555.9,
      "bb_lower": 3359.5,
      "vol_ratio": 1.24,
      "signals": {
        "ma": {
          "score": -1,
          "label": "MA25割れ",
          "icon": "↘",
          "type": "sell"
        },
        "rsi": {
          "score": 2,
          "label": "RSI 43.8 押し目",
          "icon": "🎯",
          "type": "buy"
        },
        "macd": {
          "score": 1,
          "label": "MACD強気",
          "icon": "🔺",
          "type": "buy"
        },
        "bb": {
          "score": -1,
          "label": "下半分",
          "icon": "📉",
          "type": "sell"
        },
        "vol": {
          "score": 0,
          "label": "1.2倍",
          "icon": "📊",
          "type": "neutral"
        }
      },
      "total_score": 1,
      "overall": {
        "label": "やや強気",
        "color": "#44aadd",
        "icon": "🔵"
      },
      "checks": [
        {
          "label": "MA上向き＋株価がMA上",
          "ok": false
        },
        {
          "label": "日足押し目 RSI 40-60圏",
          "ok": true
        },
        {
          "label": "直近陽線 or 5MA反発確認",
          "ok": false
        },
        {
          "label": "出来高20日平均以上",
          "ok": true
        }
      ]
    },
    {
      "code": "9501.T",
      "name": "東京電力HD",
      "sector": "エネルギー",
      "theme": "データセンター電力需要増。原発再稼働期待",
      "risk": "高",
      "error": false,
      "date": "2026-05-14",
      "close": 609.0,
      "open": 611.0,
      "change": -3.6,
      "change_pct": -0.59,
      "ma5": 630.1,
      "ma25": 624.0,
      "ma75": 638.8,
      "rsi": 46.1,
      "macd": -3.7,
      "macd_signal": -5.9,
      "bb_upper": 662.7,
      "bb_lower": 574.9,
      "vol_ratio": 0.79,
      "signals": {
        "ma": {
          "score": -1,
          "label": "MA25割れ",
          "icon": "↘",
          "type": "sell"
        },
        "rsi": {
          "score": 2,
          "label": "RSI 46.1 押し目",
          "icon": "🎯",
          "type": "buy"
        },
        "macd": {
          "score": 1,
          "label": "MACD強気",
          "icon": "🔺",
          "type": "buy"
        },
        "bb": {
          "score": -1,
          "label": "下半分",
          "icon": "📉",
          "type": "sell"
        },
        "vol": {
          "score": 0,
          "label": "0.8倍",
          "icon": "📊",
          "type": "neutral"
        }
      },
      "total_score": 1,
      "overall": {
        "label": "やや強気",
        "color": "#44aadd",
        "icon": "🔵"
      },
      "checks": [
        {
          "label": "MA上向き＋株価がMA上",
          "ok": false
        },
        {
          "label": "日足押し目 RSI 40-60圏",
          "ok": true
        },
        {
          "label": "直近陽線 or 5MA反発確認",
          "ok": false
        },
        {
          "label": "出来高20日平均以上",
          "ok": false
        }
      ]
    },
    {
      "code": "6146.T",
      "name": "ディスコ",
      "sector": "AI・半導体",
      "theme": "半導体切断・研磨装置で世界シェア首位級",
      "risk": "中",
      "error": false,
      "date": "2026-05-14",
      "close": 70000.0,
      "open": 73500.0,
      "change": -2840.0,
      "change_pct": -3.9,
      "ma5": 72804.0,
      "ma25": 71574.0,
      "ma75": 69896.1,
      "rsi": 46.4,
      "macd": 1039.1,
      "macd_signal": 1496.0,
      "bb_upper": 77403.4,
      "bb_lower": 68653.6,
      "vol_ratio": 0.76,
      "signals": {
        "ma": {
          "score": -1,
          "label": "MA25割れ",
          "icon": "↘",
          "type": "sell"
        },
        "rsi": {
          "score": 2,
          "label": "RSI 46.4 押し目",
          "icon": "🎯",
          "type": "buy"
        },
        "macd": {
          "score": -1,
          "label": "MACD弱気",
          "icon": "▽",
          "type": "sell"
        },
        "bb": {
          "score": -1,
          "label": "下半分",
          "icon": "📉",
          "type": "sell"
        },
        "vol": {
          "score": 0,
          "label": "0.8倍",
          "icon": "📊",
          "type": "neutral"
        }
      },
      "total_score": -1,
      "overall": {
        "label": "中立・様子見",
        "color": "#8899aa",
        "icon": "⚪"
      },
      "checks": [
        {
          "label": "MA上向き＋株価がMA上",
          "ok": false
        },
        {
          "label": "日足押し目 RSI 40-60圏",
          "ok": true
        },
        {
          "label": "直近陽線 or 5MA反発確認",
          "ok": false
        },
        {
          "label": "出来高20日平均以上",
          "ok": false
        }
      ]
    },
    {
      "code": "1801.T",
      "name": "大成建設",
      "sector": "建設",
      "theme": "スーパーゼネコン。防災・国土強靭化の恩恵",
      "risk": "低",
      "error": false,
      "date": "2026-05-14",
      "close": 16045.0,
      "open": 17515.0,
      "change": -1810.0,
      "change_pct": -10.14,
      "ma5": 17476.0,
      "ma25": 16578.8,
      "ma75": 16925.2,
      "rsi": 44.8,
      "macd": 216.9,
      "macd_signal": 124.7,
      "bb_upper": 18216.1,
      "bb_lower": 15048.9,
      "vol_ratio": 2.25,
      "signals": {
        "ma": {
          "score": -1,
          "label": "MA25割れ",
          "icon": "↘",
          "type": "sell"
        },
        "rsi": {
          "score": 2,
          "label": "RSI 44.8 押し目",
          "icon": "🎯",
          "type": "buy"
        },
        "macd": {
          "score": 1,
          "label": "MACD強気",
          "icon": "🔺",
          "type": "buy"
        },
        "bb": {
          "score": -1,
          "label": "下半分",
          "icon": "📉",
          "type": "sell"
        },
        "vol": {
          "score": -2,
          "label": "出来高2.3倍↓",
          "icon": "🔕",
          "type": "sell"
        }
      },
      "total_score": -1,
      "overall": {
        "label": "中立・様子見",
        "color": "#8899aa",
        "icon": "⚪"
      },
      "checks": [
        {
          "label": "MA上向き＋株価がMA上",
          "ok": false
        },
        {
          "label": "日足押し目 RSI 40-60圏",
          "ok": true
        },
        {
          "label": "直近陽線 or 5MA反発確認",
          "ok": false
        },
        {
          "label": "出来高20日平均以上",
          "ok": true
        }
      ]
    },
    {
      "code": "1605.T",
      "name": "INPEX",
      "sector": "エネルギー",
      "theme": "国内最大の石油・天然ガス開発。高配当",
      "risk": "中",
      "error": false,
      "date": "2026-05-14",
      "close": 3920.0,
      "open": 4000.0,
      "change": -10.0,
      "change_pct": -0.25,
      "ma5": 3886.0,
      "ma25": 4045.2,
      "ma75": 3986.9,
      "rsi": 44.7,
      "macd": -85.5,
      "macd_signal": -83.5,
      "bb_upper": 4248.5,
      "bb_lower": 3707.4,
      "vol_ratio": 0.88,
      "signals": {
        "ma": {
          "score": -1,
          "label": "MA25割れ",
          "icon": "↘",
          "type": "sell"
        },
        "rsi": {
          "score": 2,
          "label": "RSI 44.7 押し目",
          "icon": "🎯",
          "type": "buy"
        },
        "macd": {
          "score": -1,
          "label": "MACD弱気",
          "icon": "▽",
          "type": "sell"
        },
        "bb": {
          "score": -1,
          "label": "下半分",
          "icon": "📉",
          "type": "sell"
        },
        "vol": {
          "score": 0,
          "label": "0.9倍",
          "icon": "📊",
          "type": "neutral"
        }
      },
      "total_score": -1,
      "overall": {
        "label": "中立・様子見",
        "color": "#8899aa",
        "icon": "⚪"
      },
      "checks": [
        {
          "label": "MA上向き＋株価がMA上",
          "ok": false
        },
        {
          "label": "日足押し目 RSI 40-60圏",
          "ok": true
        },
        {
          "label": "直近陽線 or 5MA反発確認",
          "ok": false
        },
        {
          "label": "出来高20日平均以上",
          "ok": false
        }
      ]
    },
    {
      "code": "7203.T",
      "name": "トヨタ自動車",
      "sector": "自動車",
      "theme": "世界首位。来期2ケタ増益予想。自動運転投資",
      "risk": "低",
      "error": false,
      "date": "2026-05-14",
      "close": 3008.0,
      "open": 2944.0,
      "change": 68.5,
      "change_pct": 2.33,
      "ma5": 2914.7,
      "ma25": 3163.9,
      "ma75": 3375.9,
      "rsi": 41.5,
      "macd": -109.1,
      "macd_signal": -96.3,
      "bb_upper": 3489.6,
      "bb_lower": 2766.9,
      "vol_ratio": 1.2,
      "signals": {
        "ma": {
          "score": -1,
          "label": "MA25割れ",
          "icon": "↘",
          "type": "sell"
        },
        "rsi": {
          "score": 2,
          "label": "RSI 41.5 押し目",
          "icon": "🎯",
          "type": "buy"
        },
        "macd": {
          "score": -1,
          "label": "MACD弱気",
          "icon": "▽",
          "type": "sell"
        },
        "bb": {
          "score": -1,
          "label": "下半分",
          "icon": "📉",
          "type": "sell"
        },
        "vol": {
          "score": 0,
          "label": "1.2倍",
          "icon": "📊",
          "type": "neutral"
        }
      },
      "total_score": -1,
      "overall": {
        "label": "中立・様子見",
        "color": "#8899aa",
        "icon": "⚪"
      },
      "checks": [
        {
          "label": "MA上向き＋株価がMA上",
          "ok": false
        },
        {
          "label": "日足押し目 RSI 40-60圏",
          "ok": true
        },
        {
          "label": "直近陽線 or 5MA反発確認",
          "ok": true
        },
        {
          "label": "出来高20日平均以上",
          "ok": true
        }
      ]
    },
    {
      "code": "7013.T",
      "name": "IHI",
      "sector": "防衛・造船",
      "theme": "航空エンジン、防衛、宇宙。エネルギー転換にも注目",
      "risk": "中",
      "error": false,
      "date": "2026-05-14",
      "close": 2679.5,
      "open": 2750.0,
      "change": -153.0,
      "change_pct": -5.4,
      "ma5": 2849.4,
      "ma25": 3081.5,
      "ma75": 3551.4,
      "rsi": 31.1,
      "macd": -161.6,
      "macd_signal": -153.3,
      "bb_upper": 3334.3,
      "bb_lower": 2691.6,
      "vol_ratio": 1.15,
      "signals": {
        "ma": {
          "score": -1,
          "label": "MA25割れ",
          "icon": "↘",
          "type": "sell"
        },
        "rsi": {
          "score": 0,
          "label": "RSI 31.1",
          "icon": "〜",
          "type": "neutral"
        },
        "macd": {
          "score": -2,
          "label": "DCクロス",
          "icon": "⚠️",
          "type": "sell"
        },
        "bb": {
          "score": -2,
          "label": "-2σ割れ",
          "icon": "💥",
          "type": "sell"
        },
        "vol": {
          "score": 0,
          "label": "1.2倍",
          "icon": "📊",
          "type": "neutral"
        }
      },
      "total_score": -5,
      "overall": {
        "label": "売り検討",
        "color": "#ff5533",
        "icon": "🔴"
      },
      "checks": [
        {
          "label": "MA上向き＋株価がMA上",
          "ok": false
        },
        {
          "label": "日足押し目 RSI 40-60圏",
          "ok": false
        },
        {
          "label": "直近陽線 or 5MA反発確認",
          "ok": false
        },
        {
          "label": "出来高20日平均以上",
          "ok": true
        }
      ]
    },
    {
      "code": "7011.T",
      "name": "三菱重工業",
      "sector": "防衛・造船",
      "theme": "防衛最大手。防衛費GDP比2%目標で長期追い風",
      "risk": "低",
      "error": false,
      "date": "2026-05-14",
      "close": 4162.0,
      "open": 4405.0,
      "change": -244.0,
      "change_pct": -5.54,
      "ma5": 4352.4,
      "ma25": 4596.5,
      "ma75": 4681.6,
      "rsi": 35.4,
      "macd": -87.6,
      "macd_signal": -45.4,
      "bb_upper": 4881.7,
      "bb_lower": 4220.0,
      "vol_ratio": 1.51,
      "signals": {
        "ma": {
          "score": -1,
          "label": "MA25割れ",
          "icon": "↘",
          "type": "sell"
        },
        "rsi": {
          "score": 0,
          "label": "RSI 35.4",
          "icon": "〜",
          "type": "neutral"
        },
        "macd": {
          "score": -1,
          "label": "MACD弱気",
          "icon": "▽",
          "type": "sell"
        },
        "bb": {
          "score": -2,
          "label": "-2σ割れ",
          "icon": "💥",
          "type": "sell"
        },
        "vol": {
          "score": -2,
          "label": "出来高1.5倍↓",
          "icon": "🔕",
          "type": "sell"
        }
      },
      "total_score": -6,
      "overall": {
        "label": "強い売り",
        "color": "#ff2244",
        "icon": "🔴🔴"
      },
      "checks": [
        {
          "label": "MA上向き＋株価がMA上",
          "ok": false
        },
        {
          "label": "日足押し目 RSI 40-60圏",
          "ok": false
        },
        {
          "label": "直近陽線 or 5MA反発確認",
          "ok": false
        },
        {
          "label": "出来高20日平均以上",
          "ok": true
        }
      ]
    },
    {
      "code": "5401.T",
      "name": "日本製鉄",
      "sector": "素材",
      "theme": "粗鋼国内首位。USスチール買収。高配当・PBR割安",
      "risk": "中",
      "error": false,
      "date": "2026-05-14",
      "close": 556.2,
      "open": 569.2,
      "change": -3.2,
      "change_pct": -0.57,
      "ma5": 561.4,
      "ma25": 582.9,
      "ma75": 607.3,
      "rsi": 34.3,
      "macd": -9.0,
      "macd_signal": -6.8,
      "bb_upper": 608.6,
      "bb_lower": 551.1,
      "vol_ratio": 1.96,
      "signals": {
        "ma": {
          "score": -1,
          "label": "MA25割れ",
          "icon": "↘",
          "type": "sell"
        },
        "rsi": {
          "score": 0,
          "label": "RSI 34.3",
          "icon": "〜",
          "type": "neutral"
        },
        "macd": {
          "score": -1,
          "label": "MACD弱気",
          "icon": "▽",
          "type": "sell"
        },
        "bb": {
          "score": -2,
          "label": "-2σ割れ",
          "icon": "💥",
          "type": "sell"
        },
        "vol": {
          "score": -2,
          "label": "出来高2.0倍↓",
          "icon": "🔕",
          "type": "sell"
        }
      },
      "total_score": -6,
      "overall": {
        "label": "強い売り",
        "color": "#ff2244",
        "icon": "🔴🔴"
      },
      "checks": [
        {
          "label": "MA上向き＋株価がMA上",
          "ok": false
        },
        {
          "label": "日足押し目 RSI 40-60圏",
          "ok": false
        },
        {
          "label": "直近陽線 or 5MA反発確認",
          "ok": false
        },
        {
          "label": "出来高20日平均以上",
          "ok": true
        }
      ]
    }
  ]
}